scrapy_zyte_api/__init__.py
scrapy_zyte_api/__version__.py
scrapy_zyte_api/_annotations.py
scrapy_zyte_api/_cookies.py
scrapy_zyte_api/_middlewares.py
scrapy_zyte_api/_page_inputs.py
scrapy_zyte_api/_params.py
scrapy_zyte_api/_request_fingerprinter.py
scrapy_zyte_api/_serialization.py
scrapy_zyte_api/_session.py
scrapy_zyte_api/addon.py
scrapy_zyte_api/handler.py
scrapy_zyte_api/providers.py
scrapy_zyte_api/py.typed
scrapy_zyte_api/responses.py
scrapy_zyte_api/utils.py
scrapy_zyte_api-0.32.0.dist-info/METADATA
scrapy_zyte_api-0.32.0.dist-info/WHEEL
scrapy_zyte_api-0.32.0.dist-info/licenses/LICENSE.txt
scrapy_zyte_api-0.32.0.dist-info/RECORD
